{
  "contenidos": [
    {
      "id": "c_z5c7n8pmpl3722a",
      "name": "Casa Trabuco Vendida",
      "type": "image",
      "duration": 19,
      "thumbnailUrl": "https://github.com/teamdigitalfix2/display-fix-data/blob/main/images/casa%20vendida%20trabuco.png?raw=true",
      "mediaUrl": "https://github.com/teamdigitalfix2/display-fix-data/blob/main/images/casa%20vendida%20trabuco.png?raw=true",
      "order": 1,
      "active": true
    },
    {
      "id": "c_d47dqxzmpl39iaj",
      "name": "Chalet Rosario",
      "type": "image",
      "duration": 19,
      "thumbnailUrl": "https://github.com/teamdigitalfix2/display-fix-data/blob/main/images/chalet%20rosario.png?raw=true",
      "mediaUrl": "https://github.com/teamdigitalfix2/display-fix-data/blob/main/images/chalet%20rosario.png?raw=true",
      "order": 2,
      "active": true
    },
    {
      "id": "c_l07r2mtmpl39vf8",
      "name": "Consejos inmobiliarios",
      "type": "image",
      "duration": 19,
      "thumbnailUrl": "https://github.com/teamdigitalfix2/display-fix-data/blob/main/images/consejos%20inmobiliarios.png?raw=true",
      "mediaUrl": "https://github.com/teamdigitalfix2/display-fix-data/blob/main/images/consejos%20inmobiliarios.png?raw=true",
      "order": 3,
      "active": true
    },
    {
      "id": "c_1ey3vvimpl3a7v3",
      "name": "Descubre VVA",
      "type": "image",
      "duration": 20,
      "thumbnailUrl": "https://github.com/teamdigitalfix2/display-fix-data/blob/main/images/descubre%20vva%20del%20rosario.png?raw=true",
      "mediaUrl": "https://github.com/teamdigitalfix2/display-fix-data/blob/main/images/descubre%20vva%20del%20rosario.png?raw=true",
      "order": 4,
      "active": true
    },
    {
      "id": "c_cdh4zjumpl3amwj",
      "name": "EXP Realty",
      "type": "image",
      "duration": 20,
      "thumbnailUrl": "https://github.com/teamdigitalfix2/display-fix-data/blob/main/images/exp%20realty.png?raw=true",
      "mediaUrl": "https://github.com/teamdigitalfix2/display-fix-data/blob/main/images/exp%20realty.png?raw=true",
      "order": 5,
      "active": true
    },
    {
      "id": "c_zjoqa3qmpl3axma",
      "name": "Jubenial ",
      "type": "image",
      "duration": 20,
      "thumbnailUrl": "https://github.com/teamdigitalfix2/display-fix-data/blob/main/images/jubenial.png?raw=true",
      "mediaUrl": "https://github.com/teamdigitalfix2/display-fix-data/blob/main/images/jubenial.png?raw=true",
      "order": 6,
      "active": true
    },
    {
      "id": "c_tcbwswkmpl3b6xz",
      "name": "la Antilla Promociones",
      "type": "image",
      "duration": 20,
      "thumbnailUrl": "https://github.com/teamdigitalfix2/display-fix-data/blob/main/images/la%20antilla%20promociones.png?raw=true",
      "mediaUrl": "https://github.com/teamdigitalfix2/display-fix-data/blob/main/images/la%20antilla%20promociones.png?raw=true",
      "order": 7,
      "active": true
    },
    {
      "id": "c_a6bi572mpl3buj5",
      "name": "la antilla video",
      "type": "video",
      "duration": 20,
      "thumbnailUrl": "https://github.com/teamdigitalfix2/display-fix-data/blob/main/images/la%20antilla%20video.png?raw=true",
      "mediaUrl": "https://github.com/teamdigitalfix2/display-fix-data/blob/main/images/la%20antilla%20video.png?raw=true",
      "order": 8,
      "active": true
    },
    {
      "id": "c_atw8a2fmpl3c7cb",
      "name": "livve",
      "type": "video",
      "duration": 30,
      "thumbnailUrl": "https://github.com/teamdigitalfix2/display-fix-data/blob/main/images/livve.png?raw=true",
      "mediaUrl": "https://github.com/teamdigitalfix2/display-fix-data/blob/main/images/livve.png?raw=true",
      "order": 9,
      "active": true
    },
    {
      "id": "c_ghc9sg9mpl3chly",
      "name": "obre nueva andalucia",
      "type": "image",
      "duration": 20,
      "thumbnailUrl": "https://github.com/teamdigitalfix2/display-fix-data/blob/main/images/obrea%20nueva%20andalucia%C3%A7.png?raw=true",
      "mediaUrl": "https://github.com/teamdigitalfix2/display-fix-data/blob/main/images/obrea%20nueva%20andalucia%C3%A7.png?raw=true",
      "order": 10,
      "active": true
    },
    {
      "id": "c_z2suhgtmpl3csx7",
      "name": "seag video 1",
      "type": "video",
      "duration": 30,
      "thumbnailUrl": "https://github.com/teamdigitalfix2/display-fix-data/blob/main/images/seag.png?raw=true",
      "mediaUrl": "https://github.com/teamdigitalfix2/display-fix-data/blob/main/images/seag.png?raw=true",
      "order": 11,
      "active": true
    },
    {
      "id": "c_1qdk17ompl3d33a",
      "name": "seag video 2 ",
      "type": "video",
      "duration": 30,
      "thumbnailUrl": "https://github.com/teamdigitalfix2/display-fix-data/blob/main/images/seag2.png?raw=true",
      "mediaUrl": "https://github.com/teamdigitalfix2/display-fix-data/blob/main/images/seag2.png?raw=true",
      "order": 12,
      "active": true
    }
  ],
  "solicitudes": []
}